{
  "name": "2_reps_isolation_OFF_160915-043052",
  "counters": [
    {
      "name": "prediction_counter",
      "count": 3484258
    },
    {
      "name": "queued_predictions",
      "count": 515741
    },
    {
      "name": "update_counter",
      "count": 0
    },
    {
      "name": "queued_updates",
      "count": 0
    },
    {
      "name": "spark_svm:prediction_counter",
      "count": 2294452
    },
    {
      "name": "pred_ones_counter",
      "count": 3484130
    },
    {
      "name": "pred_zeros_counter",
      "count": 129
    },
    {
      "name": "spark_svm:172.21.0.5:6001:prediction_counter",
      "count": 1142447
    },
    {
      "name": "spark_svm:172.21.0.4:6001:prediction_counter",
      "count": 1152005
    }
  ],
  "ratio_counters": [
    {
      "name": "prediction accuracy ratio",
      "ratio": null
    },
    {
      "name": "cache_hits",
      "ratio": 0.0
    },
    {
      "name": "update_cache_hits",
      "ratio": null
    },
    {
      "name": "digits accuracy ratio",
      "ratio": 0.5000440552783246
    }
  ],
  "histograms": [
    {
      "name": "prediction_latency",
      "min": 23194,
      "max": 5362408,
      "mean": 2775134.690418288,
      "std": 1486972.8519155787,
      "p95": 5047391.0,
      "p99": 5241822.79,
      "p50": 2824176.0
    },
    {
      "name": "straggler_blocking_prediction_latency",
      "min": 5140,
      "max": 17293430,
      "mean": 8866596.986806907,
      "std": 4993467.968617205,
      "p95": 16497652.75,
      "p99": 17108766.02,
      "p50": 8988375.5
    },
    {
      "name": "in_time_predictions",
      "min": 0,
      "max": 0,
      "mean": 0.0,
      "std": 0.0,
      "p95": 0.0,
      "p99": 0.0,
      "p50": 0.0
    },
    {
      "name": "update_latency",
      "min": 0,
      "max": 0,
      "mean": 0.0,
      "std": 0.0,
      "p95": 0.0,
      "p99": 0.0,
      "p50": 0.0
    },
    {
      "name": "spark_svm:model_latency",
      "min": 1905,
      "max": 31645,
      "mean": 15250.67582684825,
      "std": 2658.9943238051957,
      "p95": 18704.75,
      "p99": 22716.75,
      "p50": 15465.0
    },
    {
      "name": "spark_svm:model_batch_size",
      "min": 4,
      "max": 817,
      "mean": 626.5570726379028,
      "std": 165.74907694136875,
      "p95": 770.8499999999999,
      "p99": 795.0,
      "p50": 676.0
    },
    {
      "name": "spark_svm:172.21.0.5:6001:model_latency",
      "min": 1000,
      "max": 31645,
      "mean": 15241.931541828793,
      "std": 2613.5391928000337,
      "p95": 18619.0,
      "p99": 22710.0,
      "p50": 15408.0
    },
    {
      "name": "spark_svm:172.21.0.5:6001:model_batch_size",
      "min": 4,
      "max": 817,
      "mean": 621.9090909090909,
      "std": 166.82187188138057,
      "p95": 771.0,
      "p99": 795.0,
      "p50": 671.0
    },
    {
      "name": "spark_svm:172.21.0.4:6001:model_latency",
      "min": 1926,
      "max": 28339,
      "mean": 15304.592655642024,
      "std": 2587.0651967835417,
      "p95": 18659.0,
      "p99": 22578.0,
      "p50": 15556.0
    },
    {
      "name": "spark_svm:172.21.0.4:6001:model_batch_size",
      "min": 13,
      "max": 808,
      "mean": 631.2356164383562,
      "std": 164.57530851788264,
      "p95": 770.0,
      "p99": 794.74,
      "p50": 681.0
    }
  ],
  "meters": [
    {
      "name": "prediction_thruput",
      "rate": 87053.9741554845,
      "unit": "events per second"
    },
    {
      "name": "update_thruput",
      "rate": 0.0,
      "unit": "events per second"
    },
    {
      "name": "spark_svm:model_thruput",
      "rate": 57320.52361251515,
      "unit": "events per second"
    },
    {
      "name": "spark_svm:172.21.0.5:6001:model_thruput",
      "rate": 28540.87173736783,
      "unit": "events per second"
    },
    {
      "name": "spark_svm:172.21.0.4:6001:model_thruput",
      "rate": 28779.651875147316,
      "unit": "events per second"
    },
    {
      "name": "spark_svm:cache_included_thruput",
      "rate": 8.172839918409565,
      "unit": "events per second"
    }
  ]
}